[
    {
        "name":"猕猴桃",
        "price":15,
        "inputC":false,
        "num":1,
        "id":0,
        "img1":"https://ss0.bdstatic.com/70cFvHSh_Q1YnxGkpoWK1HF6hhy/it/u=2984334905,3284066003&fm=26&gp=0.jpg"
    },
    {
        "name":"草莓",
        "price":10,
        "inputC":false,
        "num":1,
        "id":1,
        "img1":"https://ss3.bdstatic.com/70cFv8Sh_Q1YnxGkpoWK1HF6hhy/it/u=3095531234,90829183&fm=26&gp=0.jpg"
    },
    {
        "name":"葡萄",
        "price":5,
        "inputC":false,
        "num":1,
        "id":2,
        "img1":"https://ss1.bdstatic.com/70cFvXSh_Q1YnxGkpoWK1HF6hhy/it/u=2288558266,4253441191&fm=26&gp=0.jpg"
    }
]